cria.py
cria-1.6.6.dist-info/LICENSE.md
cria-1.6.6.dist-info/METADATA
cria-1.6.6.dist-info/WHEEL
cria-1.6.6.dist-info/RECORD
