Metadata-Version: 2.1
Name: cria
Version: 1.6.6
Summary: Run AI locally with as little friction as possible.
License: MIT
Author: leftmove
Requires-Python: >=3.8,<4.0
Classifier: License :: OSI Approved :: MIT License
Classifier: Programming Language :: Python :: 3
Classifier: Programming Language :: Python :: 3.8
Classifier: Programming Language :: Python :: 3.9
Classifier: Programming Language :: Python :: 3.10
Classifier: Programming Language :: Python :: 3.11
Classifier: Programming Language :: Python :: 3.12
Requires-Dist: ollama (>=0.1.8,<0.2.0)
Requires-Dist: psutil (>=5.9.8,<6.0.0)
